FirstLib/__init__.py
FirstLib/layers.py
FirstLib/loggingin.py
FirstLib/speedfilein.py
FirstLib/tensorclass.py
firstlib-0.1.dist-info/METADATA
firstlib-0.1.dist-info/WHEEL
firstlib-0.1.dist-info/top_level.txt
firstlib-0.1.dist-info/RECORD
