Metadata-Version: 2.1
Name: firstlib
Version: 0.1
Summary: This is myh first module on python.
Home-page: https://github.com/Mun-Robbery
Author: antrisole
Author-email: gleb.zar.03@mail.ru
Project-URL: GitHub, https://github.com/Mun-Robbery
Keywords: files speedfiles
Classifier: Programming Language :: Python :: 3.11
Classifier: License :: OSI Approved :: MIT License
Classifier: Operating System :: OS Independent
Requires-Python: >=3.6
Requires-Dist: requests >=2.25.1
